LICENSE.txt
MANIFEST.in
README.md
VERSION
setup.cfg
setup.py
./deepracer_env_state/__init__.py
./deepracer_env_state/composite_state.py
./deepracer_env_state/deepracer_env_data.py
./deepracer_env_state/deepracer_env_state.py
./deepracer_env_state/state_interface.py
./deepracer_env_state/agent/__init__.py
./deepracer_env_state/agent/action.py
./deepracer_env_state/agent/agent.py
./deepracer_env_state/agent/constants.py
./deepracer_env_state/agent/pose.py
./deepracer_env_state/agent/status.py
./deepracer_env_state/agent/utils.py
./deepracer_env_state/track/__init__.py
./deepracer_env_state/track/track.py
deepracer_env_state.egg-info/PKG-INFO
deepracer_env_state.egg-info/SOURCES.txt
deepracer_env_state.egg-info/dependency_links.txt
deepracer_env_state.egg-info/requires.txt
deepracer_env_state.egg-info/top_level.txt
test/test_composite_state.py
test/test_deepracer_env_data.py
test/test_deepracer_env_state.py